dpone_datagenie/__init__.py
dpone_datagenie/correlated.py
dpone_datagenie/generate.py
dpone_datagenie/outlier.py
dpone_datagenie/plotting.py
dpone_datagenie/supervised_mix.py
dpone_datagenie/supervised_num.py
dpone_datagenie/unsupervised.py
dpone_datagenie-0.1.1.dist-info/LICENSE
dpone_datagenie-0.1.1.dist-info/METADATA
dpone_datagenie-0.1.1.dist-info/WHEEL
dpone_datagenie-0.1.1.dist-info/RECORD
