Metadata-Version: 2.1
Name: dpone-datagenie
Version: 0.1.1
Summary:  Synthetic DataGen is a powerful online library designed to generate synthetic data sets for various use cases. It leverages advanced algorithms and customizable parameters to create realistic data that closely mimics real-world data while ensuring privacy and security.
Author:  NITISH MISHRA
Author-email: nitishmishra6057@gmail.com
Requires-Python: >=3.12,<4.0
Classifier: Programming Language :: Python :: 3
Classifier: Programming Language :: Python :: 3.12
Requires-Dist: imblearn (>=0.0,<0.1)
Requires-Dist: matplotlib (>=3.8.4,<4.0.0)
Requires-Dist: numpy (>=1.26.4,<2.0.0)
Requires-Dist: pandas (>=2.2.2,<3.0.0)
Requires-Dist: seaborn (>=0.13.2,<0.14.0)
